[
  {
    "image": "\/data\/upload\/1\/45c8162a-img_720.jpg",
    "id": 1,
    "choice": "No Trucks",
    "annotator": 1,
    "annotation_id": 1,
    "created_at": "2025-01-26T12:32:24.421427Z",
    "updated_at": "2025-01-26T12:32:24.421427Z",
    "lead_time": 35.477
  },
  {
    "image": "\/data\/upload\/1\/e96e1f35-img_721.jpg",
    "id": 2,
    "choice": "No Trucks",
    "annotator": 1,
    "annotation_id": 2,
    "created_at": "2025-01-26T12:32:41.790619Z",
    "updated_at": "2025-01-26T12:32:41.790619Z",
    "lead_time": 11.368
  },
  {
    "image": "\/data\/upload\/1\/6aa68b17-img_722.jpg",
    "id": 3,
    "choice": "No Trucks",
    "annotator": 1,
    "annotation_id": 3,
    "created_at": "2025-01-26T12:32:53.446857Z",
    "updated_at": "2025-01-26T12:32:53.446857Z",
    "lead_time": 8.879
  },
  {
    "image": "\/data\/upload\/1\/03e6f325-img_723.jpg",
    "id": 4,
    "choice": "No Trucks",
    "annotator": 1,
    "annotation_id": 4,
    "created_at": "2025-01-26T12:33:02.849120Z",
    "updated_at": "2025-01-26T12:33:02.849120Z",
    "lead_time": 5.995
  },
  {
    "image": "\/data\/upload\/1\/8ca2c476-img_724.jpg",
    "id": 5,
    "choice": "No Trucks",
    "annotator": 1,
    "annotation_id": 5,
    "created_at": "2025-01-26T12:33:10.683296Z",
    "updated_at": "2025-01-26T12:33:10.683296Z",
    "lead_time": 5.12
  },
  {
    "image": "\/data\/upload\/1\/a5b8058a-img_725.jpg",
    "id": 6,
    "choice": "Trucks",
    "annotator": 1,
    "annotation_id": 6,
    "created_at": "2025-01-26T12:33:17.210154Z",
    "updated_at": "2025-01-26T12:33:17.210154Z",
    "lead_time": 4.331
  },
  {
    "image": "\/data\/upload\/1\/9441b03e-img_726.jpg",
    "id": 7,
    "choice": "No Trucks",
    "annotator": 1,
    "annotation_id": 7,
    "created_at": "2025-01-26T12:33:24.347339Z",
    "updated_at": "2025-01-26T12:33:24.347339Z",
    "lead_time": 5.164
  },
  {
    "image": "\/data\/upload\/1\/033e8408-img_727.jpg",
    "id": 8,
    "choice": "No Trucks",
    "annotator": 1,
    "annotation_id": 8,
    "created_at": "2025-01-26T12:33:31.092049Z",
    "updated_at": "2025-01-26T12:33:31.092049Z",
    "lead_time": 4.574
  },
  {
    "image": "\/data\/upload\/1\/a56d808e-img_728.jpg",
    "id": 9,
    "choice": "Trucks",
    "annotator": 1,
    "annotation_id": 9,
    "created_at": "2025-01-26T12:33:39.535006Z",
    "updated_at": "2025-01-26T12:33:39.535006Z",
    "lead_time": 6.277
  },
  {
    "image": "\/data\/upload\/1\/1849942b-img_729.jpg",
    "id": 10,
    "choice": "Trucks",
    "annotator": 1,
    "annotation_id": 10,
    "created_at": "2025-01-26T12:33:47.237711Z",
    "updated_at": "2025-01-26T12:33:47.237711Z",
    "lead_time": 5.573
  },
  {
    "image": "\/data\/upload\/1\/905cbf1a-img_730.jpg",
    "id": 11,
    "choice": "Trucks",
    "annotator": 1,
    "annotation_id": 11,
    "created_at": "2025-01-26T12:33:54.439920Z",
    "updated_at": "2025-01-26T12:33:54.439920Z",
    "lead_time": 5.169
  },
  {
    "image": "\/data\/upload\/1\/b31a925a-img_731.jpg",
    "id": 12,
    "choice": "No Trucks",
    "annotator": 1,
    "annotation_id": 12,
    "created_at": "2025-01-26T12:34:02.810041Z",
    "updated_at": "2025-01-26T12:34:02.810041Z",
    "lead_time": 5.803
  },
  {
    "image": "\/data\/upload\/1\/ce0814f0-img_732.jpg",
    "id": 13,
    "choice": "No Trucks",
    "annotator": 1,
    "annotation_id": 13,
    "created_at": "2025-01-26T12:34:13.223826Z",
    "updated_at": "2025-01-26T12:34:13.223826Z",
    "lead_time": 5.791
  },
  {
    "image": "\/data\/upload\/1\/a19ee722-img_733.jpg",
    "id": 14,
    "choice": "No Trucks",
    "annotator": 1,
    "annotation_id": 14,
    "created_at": "2025-01-26T12:34:21.560137Z",
    "updated_at": "2025-01-26T12:34:21.560137Z",
    "lead_time": 6.169
  },
  {
    "image": "\/data\/upload\/1\/ca34c81d-img_734.jpg",
    "id": 15,
    "choice": "Trucks",
    "annotator": 1,
    "annotation_id": 15,
    "created_at": "2025-01-26T12:34:28.377967Z",
    "updated_at": "2025-01-26T12:34:28.377967Z",
    "lead_time": 4.767
  },
  {
    "image": "\/data\/upload\/1\/53626a19-img_735.jpg",
    "id": 16,
    "choice": "No Trucks",
    "annotator": 1,
    "annotation_id": 16,
    "created_at": "2025-01-26T12:34:35.113965Z",
    "updated_at": "2025-01-26T12:34:35.113965Z",
    "lead_time": 4.809
  },
  {
    "image": "\/data\/upload\/1\/df367397-img_736.jpg",
    "id": 17,
    "choice": "No Trucks",
    "annotator": 1,
    "annotation_id": 17,
    "created_at": "2025-01-26T12:34:42.883297Z",
    "updated_at": "2025-01-26T12:34:42.883297Z",
    "lead_time": 5.896
  },
  {
    "image": "\/data\/upload\/1\/a0064955-img_737.jpg",
    "id": 18,
    "choice": "No Trucks",
    "annotator": 1,
    "annotation_id": 18,
    "created_at": "2025-01-26T12:34:51.134243Z",
    "updated_at": "2025-01-26T12:34:51.134243Z",
    "lead_time": 4.725
  },
  {
    "image": "\/data\/upload\/1\/bc46f730-img_738.jpg",
    "id": 19,
    "choice": "Trucks",
    "annotator": 1,
    "annotation_id": 19,
    "created_at": "2025-01-26T12:35:01.168761Z",
    "updated_at": "2025-01-26T12:35:01.168761Z",
    "lead_time": 7.1
  },
  {
    "image": "\/data\/upload\/1\/ea754796-img_739.jpg",
    "id": 20,
    "choice": "Trucks",
    "annotator": 1,
    "annotation_id": 20,
    "created_at": "2025-01-26T12:35:07.787818Z",
    "updated_at": "2025-01-26T12:35:07.787818Z",
    "lead_time": 4.194
  }
]